ob_dj_otp/apis/__init__.py
ob_dj_otp/apis/otp/__init__.py
ob_dj_otp/apis/otp/serializers.py
ob_dj_otp/apis/otp/urls.py
ob_dj_otp/apis/otp/views.py
ob_dj_otp/core/__init__.py
ob_dj_otp/core/otp/__init__.py
ob_dj_otp/core/otp/admin.py
ob_dj_otp/core/otp/app_settings.py
ob_dj_otp/core/otp/apps.py
ob_dj_otp/core/otp/managers.py
ob_dj_otp/core/otp/models.py
ob_dj_otp/core/otp/settings_validation.py
ob_dj_otp/core/otp/utils.py
ob_dj_otp/core/otp/migrations/0001_initial.py
ob_dj_otp/core/otp/migrations/0002_auto_20211207_1658.py
ob_dj_otp/core/otp/migrations/0003_auto_20220117_0617.py
ob_dj_otp/core/otp/migrations/0004_onetruepairing_meta.py
ob_dj_otp/core/otp/migrations/__init__.py
ob_dj_otp/core/users/__init__.py
ob_dj_otp/core/users/admin.py
ob_dj_otp/core/users/apps.py
ob_dj_otp/core/users/managers.py
ob_dj_otp/core/users/models.py
ob_dj_otp/core/users/migrations/0001_initial.py
ob_dj_otp/core/users/migrations/__init__.py
ob_dj_otp/utils/__init__.py
ob_dj_otp/utils/helpers.py
ob_dj_otp/utils/middleware.py
ob_dj_otp/utils/model.py
ob_dj_otp-0.1.1.dist-info/METADATA
ob_dj_otp-0.1.1.dist-info/WHEEL
ob_dj_otp-0.1.1.dist-info/top_level.txt
ob_dj_otp-0.1.1.dist-info/RECORD
